matrix_tools/__init__.py
matrix_tools/lib/__init__.py
matrix_tools/lib/func_ext.py
matrix_tools/lib/get_sign.py
matrix_tools/lib/py_amqp.py
matrix_tools/lib/py_logging.py
matrix_tools/lib/py_mongo.py
shopex_matrix_tools-1.4.4.dist-info/LICENSE
shopex_matrix_tools-1.4.4.dist-info/METADATA
shopex_matrix_tools-1.4.4.dist-info/WHEEL
shopex_matrix_tools-1.4.4.dist-info/top_level.txt
shopex_matrix_tools-1.4.4.dist-info/RECORD
